LICENSE
MANIFEST.in
README.rst
run.py
setup.py
sawx/__init__.py
sawx/_metadata.py
sawx/_version.py
sawx/action.py
sawx/application.py
sawx/art.py
sawx/clipboard.py
sawx/document.py
sawx/editor.py
sawx/errors.py
sawx/events.py
sawx/filesystem.py
sawx/frame.py
sawx/keybindings.py
sawx/loader.py
sawx/menubar.py
sawx/persistence.py
sawx/preferences.py
sawx/startup.py
sawx/statusbar.py
sawx/toolbar.py
sawx.egg-info/PKG-INFO
sawx.egg-info/SOURCES.txt
sawx.egg-info/dependency_links.txt
sawx.egg-info/entry_points.txt
sawx.egg-info/not-zip-safe
sawx.egg-info/requires.txt
sawx.egg-info/top_level.txt
sawx/actions/__init__.py
sawx/actions/debug.py
sawx/actions/open_recent.py
sawx/documents/__init__.py
sawx/documents/text.py
sawx/editors/__init__.py
sawx/editors/html_viewer.py
sawx/editors/text_editor.py
sawx/help/__init__.py
sawx/icons/arrow-text-24.png
sawx/icons/arrow-text-50.png
sawx/icons/arrow-text-icon-24.png
sawx/icons/arrow-text-icon-50.png
sawx/icons/hand.ico
sawx/icons/hand.png
sawx/icons/hand_closed.ico
sawx/icons/hand_closed.png
sawx/icons/icons8-add-24.png
sawx/icons/icons8-add-50.png
sawx/icons/icons8-add-file-24.png
sawx/icons/icons8-add-file-50.png
sawx/icons/icons8-add-image-24.png
sawx/icons/icons8-add-image-50.png
sawx/icons/icons8-add-to-favorites-24.png
sawx/icons/icons8-add-to-favorites-50.png
sawx/icons/icons8-align-center-24.png
sawx/icons/icons8-align-center-50.png
sawx/icons/icons8-align-justify-24.png
sawx/icons/icons8-align-justify-50.png
sawx/icons/icons8-align-left-24.png
sawx/icons/icons8-align-left-50.png
sawx/icons/icons8-align-right-24.png
sawx/icons/icons8-align-right-50.png
sawx/icons/icons8-alphabetical-sorting-24.png
sawx/icons/icons8-alphabetical-sorting-50.png
sawx/icons/icons8-ascending-sorting-24.png
sawx/icons/icons8-ascending-sorting-50.png
sawx/icons/icons8-bold-24.png
sawx/icons/icons8-bold-50.png
sawx/icons/icons8-bring-forward-24.png
sawx/icons/icons8-bring-forward-50.png
sawx/icons/icons8-bring-to-front-24.png
sawx/icons/icons8-bring-to-front-50.png
sawx/icons/icons8-chevron-down-24.png
sawx/icons/icons8-chevron-down-50.png
sawx/icons/icons8-chevron-up-24.png
sawx/icons/icons8-chevron-up-50.png
