Metadata-Version: 1.1
Name: sawx
Version: 1.5.0
Summary: Simple Application-framework for wxPython
Home-page: http://playermissile.com/sawx
Author: Rob McMullen
Author-email: feedback@playermissile.com
License: GPL
Download-URL: https://github.com/robmcmullen/sawx/archive/1.5.0.tar.gz
Platform: Windows
Platform: Linux
Platform: Mac OS-X
Platform: Unix
Classifier: Development Status :: 5 - Production/Stable
Classifier: Intended Audience :: Developers
Classifier: License :: OSI Approved :: GNU General Public License (GPL)
Classifier: Operating System :: MacOS
Classifier: Operating System :: Microsoft :: Windows
Classifier: Operating System :: OS Independent
Classifier: Operating System :: POSIX
Classifier: Operating System :: Unix
Classifier: Programming Language :: Python
Classifier: Topic :: Utilities
Classifier: Topic :: Software Development :: Libraries :: Application Frameworks
Classifier: Topic :: Software Development :: User Interfaces
